{
  "_class": "group",
  "booleanOperation": -1,
  "clippingMaskMode": 0,
  "do_objectID": "4FE16DFB-03F2-498C-AC70-4BFBB049E0F3",
  "exportOptions": {
    "_class": "exportOptions",
    "do_objectID": "450EAFC9-74FE-42F5-9F9A-05A40254587F",
    "exportFormats": [
    ],
    "includedLayerIds": [
    ],
    "layerOptions": 0,
    "shouldTrim": false
  },
  "frame": {
    "_class": "rect",
    "constrainProportions": false,
    "do_objectID": "73A49E66-14F8-46CF-89C8-61C24A3DEB6A",
    "height": 216,
    "width": 268,
    "x": 0,
    "y": 0
  },
  "groupLayout": {
    "_class": "MSImmutableFreeformGroupLayout"
  },
  "hasClickThrough": false,
  "hasClippingMask": false,
  "isFixedToViewport": false,
  "isFlippedHorizontal": false,
  "isFlippedVertical": false,
  "isLocked": false,
  "isVisible": true,
  "layerListExpandedType": 0,
  "layers": [
    {
      "class": "rectangle",
      "id": "2D1069EE-ED9F-4F37-AD14-A7AC526C9FA2"
    },
    {
      "class": "group",
      "id": "C9C9C88E-6603-437F-9855-165A957DF5FC"
    },
    {
      "class": "text",
      "id": "78EBCF52-F221-47C5-AAA3-6A6E74E71977"
    },
    {
      "class": "text",
      "id": "FCC8D5D0-27AB-4E75-91E7-E8F67CFA466D"
    },
    {
      "class": "text",
      "id": "DCDCE237-CF20-4F47-A580-E742BF59B64D"
    },
    {
      "class": "text",
      "id": "04F871B4-4618-4588-A09F-6D97B365BB48"
    }
  ],
  "name": "Group",
  "nameIsFixed": false,
  "resizingConstraint": 63,
  "resizingType": 0,
  "rotation": 0,
  "shouldBreakMaskChain": false,
  "style": {
    "_class": "style",
    "do_objectID": "BFC0A0C5-1A5F-40FE-B245-43CA88E598FE",
    "endMarkerType": 0,
    "miterLimit": 10,
    "startMarkerType": 0,
    "windingRule": 1
  }
}