{
  "_class": "group",
  "booleanOperation": -1,
  "clippingMaskMode": 0,
  "do_objectID": "B92F4FA0-BE06-4B1E-838C-C8E62EE87C7F",
  "exportOptions": {
    "_class": "exportOptions",
    "do_objectID": "E49B225C-C042-4E0B-819F-413F18E3A84D",
    "exportFormats": [
    ],
    "includedLayerIds": [
    ],
    "layerOptions": 0,
    "shouldTrim": false
  },
  "frame": {
    "_class": "rect",
    "constrainProportions": false,
    "do_objectID": "53540C87-0F60-495D-BD94-588FE089EAA7",
    "height": 44,
    "width": 385,
    "x": 753,
    "y": 16
  },
  "groupLayout": {
    "_class": "MSImmutableFreeformGroupLayout"
  },
  "hasClickThrough": false,
  "hasClippingMask": false,
  "isFixedToViewport": false,
  "isFlippedHorizontal": false,
  "isFlippedVertical": false,
  "isLocked": false,
  "isVisible": true,
  "layerListExpandedType": 2,
  "layers": [
    {
      "class": "text",
      "id": "EE7FCE70-D6A7-4F5B-8319-B50BB01017D1"
    },
    {
      "class": "group",
      "id": "6B9059EF-908D-4CFF-BA2E-E46D5A195114"
    }
  ],
  "name": "Group 10 Copy",
  "nameIsFixed": false,
  "resizingConstraint": 63,
  "resizingType": 0,
  "rotation": 0,
  "shouldBreakMaskChain": false,
  "style": {
    "_class": "style",
    "do_objectID": "E7399396-5FF2-47DA-B535-D212AF254A36",
    "endMarkerType": 0,
    "miterLimit": 10,
    "startMarkerType": 0,
    "windingRule": 1
  }
}