{
  "_class": "group",
  "booleanOperation": -1,
  "clippingMaskMode": 0,
  "do_objectID": "1DDAD03E-42A4-4470-8C56-F5B3F7DF1B50",
  "exportOptions": {
    "_class": "exportOptions",
    "do_objectID": "3AA1D45B-F0EC-4C5B-A0BB-7E7AE6D13E6F",
    "exportFormats": [
    ],
    "includedLayerIds": [
    ],
    "layerOptions": 0,
    "shouldTrim": false
  },
  "frame": {
    "_class": "rect",
    "constrainProportions": false,
    "do_objectID": "4AD261D5-3D47-4A98-A13F-FF5F30C32346",
    "height": 899,
    "width": 200,
    "x": 0,
    "y": 0
  },
  "groupLayout": {
    "_class": "MSImmutableFreeformGroupLayout"
  },
  "hasClickThrough": false,
  "hasClippingMask": false,
  "isFixedToViewport": true,
  "isFlippedHorizontal": false,
  "isFlippedVertical": false,
  "isLocked": false,
  "isVisible": true,
  "layerListExpandedType": 2,
  "layers": [
    {
      "class": "rectangle",
      "id": "AB946D54-D41A-4464-8AE5-4DB4FB3612B9"
    },
    {
      "class": "group",
      "id": "4EAA242B-6F1F-438F-9831-EDE6B1DAE47E"
    },
    {
      "class": "rectangle",
      "id": "8B8E9C78-54A4-46A6-93DE-C58091999A68"
    }
  ],
  "name": "Sidebar",
  "nameIsFixed": true,
  "resizingConstraint": 63,
  "resizingType": 0,
  "rotation": 0,
  "shouldBreakMaskChain": false,
  "style": {
    "_class": "style",
    "do_objectID": "EAE39245-8434-4B21-9C64-76A934844026",
    "endMarkerType": 0,
    "miterLimit": 10,
    "startMarkerType": 0,
    "windingRule": 1
  },
  "userInfo": {
    "com.animaapp.stc-sketch-plugin": {
      "kModelPropertiesKey": {
      }
    }
  }
}