{
  "_class": "group",
  "booleanOperation": -1,
  "clippingMaskMode": 0,
  "do_objectID": "D8C99F4C-F06E-4340-8478-675C5C203134",
  "exportOptions": {
    "_class": "exportOptions",
    "exportFormats": [
    ],
    "includedLayerIds": [
    ],
    "layerOptions": 0,
    "shouldTrim": false
  },
  "frame": {
    "_class": "rect",
    "constrainProportions": false,
    "height": 9,
    "width": 16,
    "x": 153,
    "y": 13
  },
  "groupLayout": {
    "_class": "MSImmutableFreeformGroupLayout"
  },
  "hasClickThrough": false,
  "hasClippingMask": false,
  "isFixedToViewport": false,
  "isFlippedHorizontal": false,
  "isFlippedVertical": false,
  "isLocked": false,
  "isVisible": false,
  "layerListExpandedType": 0,
  "layers": [
    {
      "class": "rectangle",
      "id": "A1DA3CDC-A200-40F3-AF9B-3F27D73BF9BD"
    },
    {
      "class": "rectangle",
      "id": "0A0DCA80-4E69-4220-A481-3DEE7E556484"
    },
    {
      "class": "rectangle",
      "id": "8290D702-C99F-4BC8-B69A-B02079219762"
    },
    {
      "class": "text",
      "id": "1875E58F-6895-4AF3-9C0D-46C23E8ABBAC"
    }
  ],
  "name": "📐Guide - Left",
  "nameIsFixed": false,
  "resizingConstraint": 63,
  "resizingType": 0,
  "rotation": 0,
  "shouldBreakMaskChain": false,
  "style": {
    "_class": "style",
    "endMarkerType": 0,
    "miterLimit": 10,
    "startMarkerType": 0,
    "windingRule": 1
  },
  "userInfo": {
    "com.animaapp.stc-sketch-plugin": {
      "kModelPropertiesKey": {
        "constraints": {
          "aspectRatio": {
            "constant": 9,
            "enabled": 1,
            "modelID": "constraint_ee004c76-9461-4a6b-b211-de8259cd4b30",
            "model_class": "ADModelConstraint",
            "model_version": 0,
            "multiplier": 16
          },
          "automatic": 1,
          "modelID": "viewConstraints_b95eb02c-473f-44a3-87a0-5915c02a4815",
          "model_class": "ADModelViewConstraints",
          "model_version": 0,
          "scaleFactor": 1
        }
      }
    }
  }
}