{
  "_class": "group",
  "booleanOperation": 0,
  "clippingMaskMode": 0,
  "do_objectID": "B8F39609-5B3B-4477-B4E7-92A3300766AD",
  "exportOptions": {
    "_class": "exportOptions",
    "do_objectID": "13BC4EAC-7878-4B0B-8C9B-8092E81E0FC1",
    "exportFormats": [
    ],
    "includedLayerIds": [
    ],
    "layerOptions": 0,
    "shouldTrim": false
  },
  "frame": {
    "_class": "rect",
    "constrainProportions": false,
    "do_objectID": "EC5F7041-F78A-42EB-B4E8-5BAF4BF2C38A",
    "height": 42,
    "width": 42,
    "x": 0,
    "y": 0
  },
  "groupLayout": {
    "_class": "MSImmutableFreeformGroupLayout"
  },
  "hasClickThrough": false,
  "hasClippingMask": false,
  "isFixedToViewport": false,
  "isFlippedHorizontal": false,
  "isFlippedVertical": false,
  "isLocked": false,
  "isVisible": true,
  "layerListExpandedType": 0,
  "layers": [
    {
      "class": "shapePath",
      "id": "45EC3006-0D61-4E92-8776-CED6B121C68B"
    },
    {
      "class": "text",
      "id": "969CEFFD-A79F-4639-862C-85E73F28F707"
    }
  ],
  "name": "key",
  "nameIsFixed": true,
  "resizingConstraint": 63,
  "resizingType": 0,
  "rotation": 0,
  "shouldBreakMaskChain": false,
  "style": {
    "_class": "style",
    "do_objectID": "48EF391D-2426-4BD9-8E17-E0C26FD49EFE",
    "endMarkerType": 0,
    "miterLimit": 10,
    "startMarkerType": 0,
    "windingRule": 1
  }
}