{
  "_class": "group",
  "booleanOperation": -1,
  "clippingMaskMode": 0,
  "do_objectID": "E390FEC8-0302-4001-95AB-FF5929349EB1",
  "exportOptions": {
    "_class": "exportOptions",
    "exportFormats": [
    ],
    "includedLayerIds": [
    ],
    "layerOptions": 0,
    "shouldTrim": false
  },
  "frame": {
    "_class": "rect",
    "constrainProportions": false,
    "height": 9,
    "width": 8,
    "x": 24,
    "y": 9
  },
  "groupLayout": {
    "_class": "MSImmutableFreeformGroupLayout"
  },
  "hasClickThrough": false,
  "hasClippingMask": false,
  "isFixedToViewport": false,
  "isFlippedHorizontal": false,
  "isFlippedVertical": false,
  "isLocked": false,
  "isVisible": false,
  "layerListExpandedType": 0,
  "layers": [
    {
      "class": "rectangle",
      "id": "E3D59621-C852-4BFB-8960-02C6EF1E8BD2"
    },
    {
      "class": "rectangle",
      "id": "AC3F6B28-7B84-47CD-8E03-A9327DC85943"
    },
    {
      "class": "rectangle",
      "id": "0B55E1BB-AFF9-4483-8265-203CDF31F567"
    },
    {
      "class": "text",
      "id": "8596E86F-B6D2-4B49-AA00-5B1F22741FE3"
    }
  ],
  "name": "📐Guide - Middle",
  "nameIsFixed": false,
  "resizingConstraint": 63,
  "resizingType": 0,
  "rotation": 0,
  "shouldBreakMaskChain": false,
  "style": {
    "_class": "style",
    "endMarkerType": 0,
    "miterLimit": 10,
    "startMarkerType": 0,
    "windingRule": 1
  }
}