{
  "_class": "group",
  "booleanOperation": -1,
  "clippingMaskMode": 0,
  "do_objectID": "F626E5FC-87D9-4BFB-91DC-DF98014AB924",
  "exportOptions": {
    "_class": "exportOptions",
    "exportFormats": [
    ],
    "includedLayerIds": [
    ],
    "layerOptions": 0,
    "shouldTrim": false
  },
  "frame": {
    "_class": "rect",
    "constrainProportions": false,
    "height": 9,
    "width": 16,
    "x": 0,
    "y": 13
  },
  "groupLayout": {
    "_class": "MSImmutableFreeformGroupLayout"
  },
  "hasClickThrough": false,
  "hasClippingMask": false,
  "isFixedToViewport": false,
  "isFlippedHorizontal": false,
  "isFlippedVertical": false,
  "isLocked": false,
  "isVisible": false,
  "layerListExpandedType": 0,
  "layers": [
    {
      "class": "rectangle",
      "id": "0E7C6D10-FED2-48BE-AD63-EBFA83EAB5AF"
    },
    {
      "class": "rectangle",
      "id": "B2643ADD-F472-4E5E-A4EF-991303154320"
    },
    {
      "class": "rectangle",
      "id": "0448D532-1B56-409D-A611-0A8D9762EA5F"
    },
    {
      "class": "text",
      "id": "3BD2F5A7-32D7-4D4A-9F45-FA01BF1B1FAD"
    }
  ],
  "name": "📐Guide - Right",
  "nameIsFixed": false,
  "resizingConstraint": 63,
  "resizingType": 0,
  "rotation": 0,
  "shouldBreakMaskChain": false,
  "style": {
    "_class": "style",
    "endMarkerType": 0,
    "miterLimit": 10,
    "startMarkerType": 0,
    "windingRule": 1
  }
}