{
  "_class": "group",
  "booleanOperation": -1,
  "clippingMaskMode": 0,
  "do_objectID": "9A181A9A-1C52-480A-9A41-DB471BAF19B8",
  "exportOptions": {
    "_class": "exportOptions",
    "exportFormats": [
    ],
    "includedLayerIds": [
    ],
    "layerOptions": 0,
    "shouldTrim": false
  },
  "frame": {
    "_class": "rect",
    "constrainProportions": false,
    "do_objectID": "83FF1A0B-1F5D-4403-A8C5-0F45E41EDEBF",
    "height": 16,
    "width": 12,
    "x": 50,
    "y": 8
  },
  "groupLayout": {
    "_class": "MSImmutableFreeformGroupLayout"
  },
  "hasClickThrough": false,
  "hasClippingMask": false,
  "isFixedToViewport": false,
  "isFlippedHorizontal": false,
  "isFlippedVertical": false,
  "isLocked": false,
  "isVisible": true,
  "layerListExpandedType": 0,
  "layers": [
    {
      "class": "shapePath",
      "id": "FE19B71F-B27E-4E1E-AD6C-C72D8ADED994"
    },
    {
      "class": "group",
      "id": "3ACA046A-671E-4969-83A9-770091520F46"
    }
  ],
  "name": "icon/photo-camera copy",
  "nameIsFixed": false,
  "resizingConstraint": 63,
  "resizingType": 0,
  "rotation": 0,
  "shouldBreakMaskChain": false,
  "style": {
    "_class": "style",
    "do_objectID": "D9B6C3A9-34EE-4CF9-AD82-EE0697B64CA2",
    "endMarkerType": 0,
    "miterLimit": 10,
    "startMarkerType": 0,
    "windingRule": 1
  },
  "userInfo": {
    "com.animaapp.stc-sketch-plugin": {
      "kModelPropertiesKey": {
        "constraints": {
          "aspectRatio": {
            "constant": 16,
            "enabled": 1,
            "modelID": "constraint_93248947-c5e9-42e1-9659-e2f4a51e2ef1",
            "model_class": "ADModelConstraint",
            "model_version": 0.1,
            "multiplier": 16
          },
          "automatic": 1,
          "modelID": "viewConstraints_dc2a54ab-75bf-42a4-9433-c97e12256435",
          "model_class": "ADModelViewConstraints",
          "model_version": 0.1,
          "scaleFactor": 1
        }
      }
    }
  }
}