{
  "_class": "group",
  "booleanOperation": -1,
  "clippingMaskMode": 0,
  "do_objectID": "4354F297-69CE-452E-9B05-CD67F5196582",
  "exportOptions": {
    "_class": "exportOptions",
    "exportFormats": [
    ],
    "includedLayerIds": [
    ],
    "layerOptions": 0,
    "shouldTrim": false
  },
  "frame": {
    "_class": "rect",
    "constrainProportions": false,
    "height": 40,
    "width": 315,
    "x": 24,
    "y": 69
  },
  "groupLayout": {
    "_class": "MSImmutableFreeformGroupLayout"
  },
  "hasClickThrough": false,
  "hasClippingMask": false,
  "isFixedToViewport": false,
  "isFlippedHorizontal": false,
  "isFlippedVertical": false,
  "isLocked": false,
  "isVisible": true,
  "layerListExpandedType": 0,
  "layers": [
    {
      "class": "group",
      "id": "1E38E815-069A-4C89-9D3B-D6F84AF9723A"
    },
    {
      "class": "group",
      "id": "7231C8B7-671C-482D-9BA2-DAA50A672E32"
    },
    {
      "class": "symbolInstance",
      "id": "1BE0DEFE-97EA-46F7-B112-9A05558588D3"
    },
    {
      "class": "text",
      "id": "EDBD800B-DC2F-4BB3-A02B-29CEF5D9875E"
    }
  ],
  "name": "component / input / 1-addons / filled copy",
  "nameIsFixed": false,
  "resizingConstraint": 63,
  "resizingType": 0,
  "rotation": 0,
  "shouldBreakMaskChain": false,
  "style": {
    "_class": "style",
    "endMarkerType": 0,
    "miterLimit": 10,
    "startMarkerType": 0,
    "windingRule": 1
  }
}