{
  "_class": "symbolInstance",
  "booleanOperation": -1,
  "clippingMaskMode": 0,
  "do_objectID": "C7B39C7A-60A5-4597-AC54-22482F4B3977",
  "exportOptions": {
    "_class": "exportOptions",
    "do_objectID": "81F1FAE5-A59F-4A30-9638-31532374B186",
    "exportFormats": [
    ],
    "includedLayerIds": [
    ],
    "layerOptions": 0,
    "shouldTrim": false
  },
  "frame": {
    "_class": "rect",
    "constrainProportions": false,
    "do_objectID": "2757CDEE-E508-4ACD-8FED-1C179201CDB5",
    "height": 48,
    "width": 150,
    "x": 24,
    "y": 408
  },
  "hasClippingMask": false,
  "horizontalSpacing": 0,
  "isFixedToViewport": false,
  "isFlippedHorizontal": false,
  "isFlippedVertical": false,
  "isLocked": false,
  "isVisible": true,
  "layerListExpandedType": 0,
  "name": "table / header copy 31",
  "nameIsFixed": false,
  "overrideValues": [
    {
      "_class": "overrideValue",
      "overrideName": "62086A6B-AABB-4D7D-AEBD-D7DBB20C1778_symbolID",
      "value": ""
    },
    {
      "_class": "overrideValue",
      "overrideName": "1C5F1257-DC26-4D02-9922-9CB41C58066A_symbolID",
      "value": ""
    },
    {
      "_class": "overrideValue",
      "overrideName": "160E0DC3-3A24-4135-B6F7-7A0BD66C853F_symbolID",
      "value": ""
    },
    {
      "_class": "overrideValue",
      "overrideName": "3BF33735-8D67-4CB7-AA36-56B897BDB49A_symbolID",
      "value": ""
    },
    {
      "_class": "overrideValue",
      "overrideName": "2FE9769B-99C3-40DD-A6B7-D7C4A016DA72_stringValue",
      "value": "20:20 Jun 8 2018"
    }
  ],
  "resizingConstraint": 63,
  "resizingType": 0,
  "rotation": 0,
  "scale": 1,
  "shouldBreakMaskChain": false,
  "style": {
    "_class": "style",
    "do_objectID": "B5F2B8E3-3061-4FDC-8E5A-F6A596137D81",
    "endMarkerType": 0,
    "miterLimit": 10,
    "startMarkerType": 0,
    "windingRule": 1
  },
  "symbolID": "24A10563-F1CA-45AA-AF7F-34B56F5648EA",
  "verticalSpacing": 0
}