{
  "_class": "group",
  "booleanOperation": -1,
  "clippingMaskMode": 0,
  "do_objectID": "F60DD2A7-EA29-4FC7-95BD-3D46344271E3",
  "exportOptions": {
    "_class": "exportOptions",
    "exportFormats": [
    ],
    "includedLayerIds": [
    ],
    "layerOptions": 0,
    "shouldTrim": false
  },
  "frame": {
    "_class": "rect",
    "constrainProportions": false,
    "height": 9,
    "width": 8,
    "x": 0,
    "y": 9
  },
  "groupLayout": {
    "_class": "MSImmutableFreeformGroupLayout"
  },
  "hasClickThrough": false,
  "hasClippingMask": false,
  "isFixedToViewport": false,
  "isFlippedHorizontal": false,
  "isFlippedVertical": false,
  "isLocked": false,
  "isVisible": false,
  "layerListExpandedType": 0,
  "layers": [
    {
      "class": "rectangle",
      "id": "2DE4890E-BE39-4737-B40D-F40EB361ABC4"
    },
    {
      "class": "rectangle",
      "id": "B350CE38-A0EF-442B-8B4D-24AA2BD484EE"
    },
    {
      "class": "rectangle",
      "id": "DAA36FFD-F010-45E6-BD39-4A431F2A327C"
    },
    {
      "class": "text",
      "id": "D96926D9-8A41-4C76-86E0-DDC79DA35807"
    }
  ],
  "name": "📐Guide - Left",
  "nameIsFixed": false,
  "resizingConstraint": 63,
  "resizingType": 0,
  "rotation": 0,
  "shouldBreakMaskChain": false,
  "style": {
    "_class": "style",
    "endMarkerType": 0,
    "miterLimit": 10,
    "startMarkerType": 0,
    "windingRule": 1
  },
  "userInfo": {
    "com.animaapp.stc-sketch-plugin": {
      "kModelPropertiesKey": {
      }
    }
  }
}