{
  "_class": "group",
  "booleanOperation": -1,
  "clippingMaskMode": 0,
  "do_objectID": "4AFBCA8A-77D4-4AB4-8197-38017543D49F",
  "exportOptions": {
    "_class": "exportOptions",
    "do_objectID": "D7EA5684-4929-4E0C-9933-36BA95398279",
    "exportFormats": [
    ],
    "includedLayerIds": [
    ],
    "layerOptions": 0,
    "shouldTrim": false
  },
  "frame": {
    "_class": "rect",
    "constrainProportions": false,
    "do_objectID": "6988FE94-A74A-4474-8092-2BAB2419683A",
    "height": 100,
    "width": 343,
    "x": 0,
    "y": 435
  },
  "groupLayout": {
    "_class": "MSImmutableFreeformGroupLayout"
  },
  "hasClickThrough": false,
  "hasClippingMask": false,
  "isFixedToViewport": false,
  "isFlippedHorizontal": false,
  "isFlippedVertical": false,
  "isLocked": false,
  "isVisible": true,
  "layerListExpandedType": 0,
  "layers": [
    {
      "class": "group",
      "id": "DD3E7E07-569D-43C1-A319-2503EFC26E57"
    },
    {
      "class": "text",
      "id": "F95F7DF7-709E-4FD3-A8BF-A4BFAD1CB892"
    },
    {
      "class": "symbolInstance",
      "id": "C8F5E0F2-21C6-4A13-9CD0-D2C9C53E5CCB"
    }
  ],
  "name": "Group 3 Copy",
  "nameIsFixed": false,
  "resizingConstraint": 63,
  "resizingType": 0,
  "rotation": 0,
  "shouldBreakMaskChain": false,
  "style": {
    "_class": "style",
    "do_objectID": "9183961E-B94E-4D20-ABC7-7EC22554D490",
    "endMarkerType": 0,
    "miterLimit": 10,
    "startMarkerType": 0,
    "windingRule": 1
  }
}