{
  "_class": "symbolInstance",
  "booleanOperation": -1,
  "clippingMaskMode": 0,
  "do_objectID": "99D09758-8F9C-4DDF-AC8B-AE808FF95CE5",
  "exportOptions": {
    "_class": "exportOptions",
    "do_objectID": "A80AE1EC-E776-4950-BDFC-FC6000DE6454",
    "exportFormats": [
    ],
    "includedLayerIds": [
    ],
    "layerOptions": 0,
    "shouldTrim": false
  },
  "frame": {
    "_class": "rect",
    "constrainProportions": false,
    "do_objectID": "9B1CAAA0-8F03-452E-98F8-81AC69B83EF1",
    "height": 1,
    "width": 375,
    "x": 0,
    "y": 119
  },
  "hasClippingMask": false,
  "horizontalSpacing": 0,
  "isFixedToViewport": false,
  "isFlippedHorizontal": false,
  "isFlippedVertical": false,
  "isLocked": false,
  "isVisible": true,
  "layerListExpandedType": 0,
  "name": "misc / border / horizontal",
  "nameIsFixed": false,
  "overrideValues": [
    {
      "_class": "overrideValue",
      "do_objectID": "6D6DF30F-AA28-4AAD-AE57-9B421842A18C",
      "overrideName": "05E54933-0281-4200-9201-F2560FEF52A7_symbolID",
      "value": "C1CEC2DD-D7D0-407B-824E-90BB74D4D33C"
    }
  ],
  "resizingConstraint": 63,
  "resizingType": 0,
  "rotation": 0,
  "scale": 1,
  "shouldBreakMaskChain": false,
  "style": {
    "_class": "style",
    "do_objectID": "8569E9FA-F166-43D6-9BBE-4CF96A7C1C33",
    "endMarkerType": 0,
    "miterLimit": 10,
    "startMarkerType": 0,
    "windingRule": 1
  },
  "symbolID": "4CAE08E7-4770-4276-B3C1-B53370BF7754",
  "userInfo": {
    "com.animaapp.stc-sketch-plugin": {
      "kModelPropertiesKey": {
      }
    }
  },
  "verticalSpacing": 0
}