{
  "_class": "artboard",
  "backgroundColor": {
    "_class": "color",
    "alpha": 1,
    "blue": 0.9725490196078431,
    "do_objectID": "DE09135E-D861-4474-87DB-6D64278DC66B",
    "green": 0.9725490196078431,
    "red": 0.9725490196078431
  },
  "booleanOperation": -1,
  "clippingMaskMode": 0,
  "do_objectID": "4BFAFB85-5581-43C2-8432-481FCBB8D97D",
  "exportOptions": {
    "_class": "exportOptions",
    "do_objectID": "B0FF791F-EF44-49D0-A180-2D22FD88BB12",
    "exportFormats": [
    ],
    "includedLayerIds": [
    ],
    "layerOptions": 0,
    "shouldTrim": false
  },
  "frame": {
    "_class": "rect",
    "constrainProportions": false,
    "do_objectID": "C4EB2E3F-66B1-4592-BC39-D10A7DCD6D73",
    "height": 2455,
    "width": 375,
    "x": -2111,
    "y": 16443
  },
  "groupLayout": {
    "_class": "MSImmutableFreeformGroupLayout"
  },
  "hasBackgroundColor": true,
  "hasClickThrough": true,
  "hasClippingMask": false,
  "horizontalRulerData": {
    "_class": "rulerData",
    "base": 0,
    "do_objectID": "94DF5836-E988-4175-8566-270725A87BCE",
    "guides": [
    ]
  },
  "includeBackgroundColorInExport": true,
  "includeInCloudUpload": true,
  "isFixedToViewport": false,
  "isFlippedHorizontal": false,
  "isFlippedVertical": false,
  "isFlowHome": false,
  "isLocked": false,
  "isVisible": true,
  "layerListExpandedType": 2,
  "layers": [
    {
      "class": "group",
      "id": "31398CEF-9CEC-4716-825B-8ED754CEA351"
    },
    {
      "class": "group",
      "id": "1AC2624B-BFBA-4479-8777-551615F751FE"
    },
    {
      "class": "group",
      "id": "7C984787-501E-415D-AC9A-D26DD61084A7"
    },
    {
      "class": "group",
      "id": "CA990054-B189-4BE4-8F71-18FC61FD24B8"
    },
    {
      "class": "group",
      "id": "60E345A0-EC39-40D5-B691-BC70498886ED"
    },
    {
      "class": "symbolInstance",
      "id": "545FF5AA-F3C9-4153-920E-FD3F2E08F4E0"
    }
  ],
  "layout": {
    "_class": "layoutGrid",
    "columnWidth": 61.75,
    "do_objectID": "8F29432C-E40E-4585-8498-89ECFD7903BE",
    "drawHorizontal": true,
    "drawHorizontalLines": false,
    "drawVertical": true,
    "gutterHeight": 8,
    "gutterWidth": 32,
    "guttersOutside": true,
    "horizontalOffset": 0,
    "isEnabled": false,
    "numberOfColumns": 4,
    "rowHeightMultiplication": 1,
    "totalWidth": 375
  },
  "name": "Mobile - Setting 1",
  "nameIsFixed": false,
  "presetDictionary": {
    "allowResizedMatching": 1,
    "height": 667,
    "name": "iPhone 8",
    "offersLandscapeVariant": 1,
    "width": 375
  },
  "resizesContent": false,
  "resizingConstraint": 63,
  "resizingType": 0,
  "rotation": 0,
  "shouldBreakMaskChain": true,
  "style": {
    "_class": "style",
    "do_objectID": "6629327D-32A4-43C0-B813-FBEAFD2E968D",
    "endMarkerType": 0,
    "miterLimit": 10,
    "startMarkerType": 0,
    "windingRule": 1
  },
  "verticalRulerData": {
    "_class": "rulerData",
    "base": 0,
    "do_objectID": "2BF4589B-CF2C-46CC-8C4F-8E7031A50835",
    "guides": [
    ]
  }
}