{
  "_class": "symbolInstance",
  "booleanOperation": -1,
  "clippingMaskMode": 0,
  "do_objectID": "4982E783-8CA2-495D-A198-23734335ED92",
  "exportOptions": {
    "_class": "exportOptions",
    "exportFormats": [
    ],
    "includedLayerIds": [
    ],
    "layerOptions": 0,
    "shouldTrim": false
  },
  "frame": {
    "_class": "rect",
    "constrainProportions": false,
    "do_objectID": "02373054-4542-4F69-848F-23B5A685A509",
    "height": 80,
    "width": 343,
    "x": 16,
    "y": 1096
  },
  "hasClippingMask": false,
  "horizontalSpacing": 0,
  "isFixedToViewport": false,
  "isFlippedHorizontal": false,
  "isFlippedVertical": false,
  "isLocked": false,
  "isVisible": true,
  "layerListExpandedType": 0,
  "name": "component / checkbox / pc",
  "nameIsFixed": false,
  "overrideValues": [
    {
      "_class": "overrideValue",
      "do_objectID": "85F51A87-6A90-4810-918F-C160DA36CDB1",
      "overrideName": "2A0E1477-1FF3-43F2-A39E-145E09C1DBFE_stringValue",
      "value": "I have read and agreed with Writer Terms"
    }
  ],
  "resizingConstraint": 41,
  "resizingType": 0,
  "rotation": 0,
  "scale": 1,
  "shouldBreakMaskChain": false,
  "style": {
    "_class": "style",
    "do_objectID": "C9A4A819-E53E-49B7-A3CA-C5A592FEA8A5",
    "endMarkerType": 0,
    "miterLimit": 10,
    "startMarkerType": 0,
    "windingRule": 1
  },
  "symbolID": "58331D33-0792-4FAE-B226-0F09C707517D",
  "verticalSpacing": 0
}